pubtools/exodus/__init__.py
pubtools/exodus/gateway.py
pubtools/exodus/task.py
pubtools/exodus/_hooks/__init__.py
pubtools/exodus/_hooks/pulp.py
pubtools/exodus/_tasks/__init__.py
pubtools/exodus/_tasks/push.py
pubtools_exodus-1.5.2.dist-info/LICENSE
pubtools_exodus-1.5.2.dist-info/METADATA
pubtools_exodus-1.5.2.dist-info/WHEEL
pubtools_exodus-1.5.2.dist-info/entry_points.txt
pubtools_exodus-1.5.2.dist-info/top_level.txt
pubtools_exodus-1.5.2.dist-info/RECORD
