Metadata-Version: 2.1
Name: pubtools-exodus
Version: 1.5.2
Summary: Utilities for interfacing with components of Red Hat's Content Delivery Network
Home-page: https://github.com/release-engineering/pubtools-exodus
License: GNU General Public License
Project-URL: Changelog, https://github.com/release-engineering/pubtools-exodus/blob/main/CHANGELOG.md
Project-URL: Documentation, https://release-engineering.github.io/pubtools-exodus
Platform: UNKNOWN
Classifier: Development Status :: 4 - Beta
Classifier: Intended Audience :: Developers
Classifier: License :: OSI Approved :: GNU General Public License v3 or later (GPLv3+)
Classifier: Programming Language :: Python :: 3
Classifier: Programming Language :: Python :: 3.6
Classifier: Topic :: Software Development :: Libraries :: Python Modules
Requires-Python: >=3.6
Requires-Dist: requests
Requires-Dist: monotonic
Requires-Dist: pubtools>=0.3.0
Requires-Dist: pushsource>=2.16.0
